.coveragerc
.pylintrc
.travis.yml
LICENSE
README.rst
requirements.txt
setup.cfg
setup.py
tox.ini
asyncat/__init__.py
asyncat/client.py
asyncat/enumeration.py
asyncat/oauth.py
asyncat/repository.py
asyncat.egg-info/PKG-INFO
asyncat.egg-info/SOURCES.txt
asyncat.egg-info/dependency_links.txt
asyncat.egg-info/not-zip-safe
asyncat.egg-info/pbr.json
asyncat.egg-info/requires.txt
asyncat.egg-info/top_level.txt
tests/__init__.py
tests/test_client.py
tests/test_repository.py